{"name":"dart:","description":"Dart System Libraries","libraries":[{"refId":"polymer_elements"},{"refId":"polymer_elements.polymer_ajax"},{"refId":"polymer_elements.polymer_anchor_point"},{"refId":"polymer_elements.polymer_collapse"},{"refId":"polymer_elements.polymer_collapse_toggle"},{"refId":"polymer_elements.polymer_file"},{"refId":"polymer_elements.polymer_flex_layout"},{"refId":"polymer_elements.polymer_flex_panel"},{"refId":"polymer_elements.polymer_localstorage"},{"refId":"polymer_elements.polymer_media_query"},{"refId":"polymer_elements.polymer_page"},{"refId":"polymer_elements.polymer_selection"},{"name":"package:polymer_elements/polymer_selector/polymer_selector.dart","refId":"polymer_elements.polymer_selector"},{"refId":"polymer_elements.polymer_xhr"},{"refId":"polymer_ui_elements"},{"refId":"polymer_ui_elements.polymer_ui_accordion"},{"refId":"polymer_ui_elements.polymer_ui_arrow"},{"refId":"polymer_ui_elements.polymer_ui_collapsible"},{"refId":"polymer_ui_elements.polymer_ui_icon"},{"refId":"polymer_ui_elements.polymer_ui_icon_button"},{"refId":"polymer_ui_elements.polymer_ui_theme_aware"},{"refId":"polymer_ui_elements.polymer_ui_toggle_button"},{"refId":"polymer_ui_elements.polymer_ui_toolbar"}],"revision":"0","location":"0","dependencies":[]}